{
  "start": "Commencer",
  "slogan": "Concentrez-vous sur le poker, pas sur les jetons",
  "players": "Joueurs",
  "smallBlind": "Petite Blind",
  "bigBlind": "Grosse Blind",
  "buyIn": "Buy-in",
  "settings": "Paramètres",
  "back": "Retour",
  "rollback": "Annuler",
  "statics": "Statistiques",
  "showdown": "Showdown",
  "Preflop": "Preflop",
  "Flop": "Flop",
  "Turn": "Turn",
  "River": "River",
  "pot": "Pot",
  "whoWins": "Qui gagne ?",
  "fold": "Fold",
  "check": "Check",
  "call": "Call",
  "raise": "Relancer",
  "allIn": "Tapis",
  "min": "Min",
  "max": "Max",
  "language": "Langue",
  "languageOptions": {
    "en-US": "Anglais",
    "ja-JP": "Japonais",
    "pt-BR": "Portugais",
    "ru-RU": "Russe",
    "fil-PH": "Philippin",
    "zh-CN": "Chinois",
    "zh-TW": "Chinois (Taïwan)",
    "zh-HK": "Chinois (Hong Kong)",
    "ko-KR": "Coréen",
    "es-AR": "Espagnol",
    "de-DE": "Allemand",
    "it-IT": "Italien",
    "fr-FR": "Français",
    "hi-IN": "Hindi",
    "th-TH": "Thaï",
    "vi-VN": "Vietnamien"
  },
  "message": {
    "atLeast2PlayersRequired": "Au moins 2 joueurs sont requis",
    "smallBlindMustBeGreaterThan0": "La petite blind doit être supérieure à 0",
    "bigBlindMustBeGreaterOrEqualToSmallBlind": "La grosse blind doit être supérieure ou égale à la petite blind",
    "buyInMustBeGreaterThanBigBlindTimes2": "Le buy-in doit être supérieur à deux fois la grosse blind",
    "selectPlayer": "Sélectionnez un joueur",
    "playerNotFound": "Joueur non trouvé"
  },
  "player": "Joueur",
  "name": "Nom",
  "chips": "Jetons",
  "game": "Jeu",
  "display": "Affichage",
  "amount": "Montant",
  "save": "Sauvegarder",
  "confirm": "Confirmer",
  "busted": "Éliminé"
}